{"passwordChecked":false,"archived":false,"attachmentsList":[],"baseCategory":{"color":"-8825528","count":0,"description":"","id":1550610041541,"name":"Z.Y Bk"},"checklist":false,"content":"You is in a religious bubble\n$Pd prodigies\nEpoch jss not recorded\nPhotos manip\n\nCrml cbç\nBt\nSteph (bn/dsgst)\nCrc fml D\n\nDsosp\nMPc\n\nStrng: fmttin 2012\nMbt\n\nB prdctv\n\nDont depend your drms on hmns","creation":1552316703893,"lastModification":1552316703893,"locked":false,"reminderFired":false,"title":"","trashed":false}