{"passwordChecked":false,"archived":false,"attachmentsList":[],"baseCategory":{"color":"-7508381","count":0,"description":"","id":1550155002203,"name":"Z.Y PJ"},"checklist":false,"content":"$1 \u003d LVL 1\n$5 \u003d LVL 2\n$15 \u003d LVL 3\n$ 25 \u003d LVL 4\n$ 50 \u003d LVL 5\n$75 \u003d LVL 6\n$100 \u003d LVL 7\n$150 \u003d LVL 8\n$200 \u003d LVL 9\n$300 \u003d LVL 10\n$500 \u003d LVL 11\n$1000 \u003d LVL 12\n$1500 \u003d LVL 13\n$2000 \u003d LVL 14\n$3500 \u003d LVL 15\n$5000 \u003d LVL 16\n$10000 \u003d LVL 17\n$15000 \u003d LVL 18\n$20000 \u003d LVL 19\n$25000 \u003d LVL 20\n$35000 \u003d LVL 21\n$50000 \u003d LVL 22\n$65000 \u003d LVL 23\n$80000 \u003d LVL 24\n$100,000 \u003d LVL 25\n$150,000 \u003d LVL 26\n$200,000 \u003d LVL 27\n$250,000 \u003d LVL 28\n$300,000 \u003d LVL 29\n$350,000 \u003d LVL 30\n$400,000 \u003d LVL 31\n$450,000 \u003d LVL 32\n$500,000 \u003d LVL 33\n$550,000 \u003d LVL 34\n$600,000 \u003d LVL 35\n$650,000 \u003d LVL 36\n$700,000 \u003d LVL 37\n$750,000 \u003d LVL 38\n$800,000 \u003d LVL 39\n$850,000 \u003d LVL 40\n\n(Maçons corrompidos mandaram passar com musica \"menininho anda ape mo ralé\" e vizinho repetiu musica; enganados, como se eu tivesse anotando dinheiro pessoal)","creation":1553279577457,"lastModification":1553279704436,"locked":false,"reminderFired":false,"title":"ZeroBay - Buyer/Seller/Escrow levels","trashed":false}