{"passwordChecked":false,"archived":false,"attachmentsList":[],"baseCategory":{"color":"-26624","count":0,"description":"","id":1550066096907,"name":"3. Floflis + HTML5 (F 1) (-31d/4d)"},"checklist":true,"content":"[ ] Hibernate\n[ ] Task Manager in taskbar\u0027s context menu\n[ ] Siacoin and mount drive\n[ ] HTML5Apps Platform\n[ ] HTML5 Player\n[ ] Kaypi Navigator\n[ ] Explorer\n[ ] DTB\n[ ] Aragon\n[ ] S/V/I (only for trust)\n[ ] Chn assist\n[ ] Live like Tails\n[ ] Live boot: detect to run x32 or x64\n[ ] Esperanto (i18n, learn)\n[ ] Colemak type course\n[ ] New Colemak layouts\n[ ] Dun\n[ ] Import previous OS (L/W/M)\n[ ] Import from mobile OS\n[ ] Resume where left\n[ ] Multilang\n[ ] Multilang docs\n[ ] User professional resume (Dat, 3Box, integrated with Ethlance and BountiesNetwork)\n[ ] More sounds\n[ ] Sound settings\n[ ] Temp UniStore (unistore.eth)\n[ ] Rcv tk for hstng, prtct both act. and unic.\n[ ] Poodle\n[ ] ETHC\n[ ] Open Knowledge\n[ ] Interactive exp: the new plnt\n[ ] How % open-source is your device\n[ ] dappstore.eth\n[ ] Virtuh (Floflis 20I2)\n[ ] Smaller taskbar, based in Cinnamon original theme\n[ ] DIY playground\n[ ] DIY keyboard layout\n[ ] DIY luminescent keyboard\n[ ] Find Windows partition, scan its programs\n[ ] Manifesto\n[ ] Floflis Committee and its \"D al\" Manifesto\n[ ] Symlink sounds from themes\n[ ] Support Windows themes\n[ ] Integration with Pinata and others\n[ ] NMC","creation":1565048275239,"lastModification":1565049547236,"locked":false,"reminderFired":false,"title":"Builds","trashed":false}