{"passwordChecked":false,"archived":false,"attachmentsList":[],"baseCategory":{"color":"-3285959","count":0,"description":"","id":1566881477637,"name":" \u0026 ip sites"},"checklist":true,"content":"[ ] Splash\n[ ] Read apps folder\n[ ] Array apps\n[ ] Read games folder\n[ ] Array games\n[ ] Read HTML5 folder\n[ ] Array HTML5\n[ ]  \n[ ] Install Cygwin\n[ ] Install Floflis subsystem\n[ ] Pin on taskbar (W, L, Mc)\n[ ] Autostart with OS (W, L, Mc)\n[ ] Run hidden from taskbar, for quickly openning menu\n[ ] Show a Cordova notification suggesting about clicking it (Alertaj)\n[ ] Open on taskbar when clicked\n[ ] Start window at bottom-left\n[ ] Close from taskbar on unfocus (1d)\n[ ]  \n[ ] List apps/games/HTML5 with order (1d)\n[ ]  \n[ ] Open user`s portable folders\n[ ] user name/photo\n[ ]  \n[ ] Enc. with password\n[ ] Games folder with special view\n[ ] Apps folder with special view (1d)\n[ ] HTML5 folder with special view (1d)\n[ ]  \n[ ] Load app in its new window (1d)\n[ ] Chromium portable-storage (1d)\n[ ] Auto-complete for all apps (1d)\n[ ]  \n[ ] https://github.com/datproject/dat-node\n[ ] Built-in Dat/IPFS/C/Y (2d)\n[ ]  \n[ ] HTML (1d)\n[ ] About (version, libs, FMWK version, license)\n[ ] Frameless window/window btns (1d)\n[ ] Symlink user folders (Windows, Mac, Linux) (3d)\n[ ] Power btn (1d)\n[ ]  \n[ ] Apps as browser tabs\n[ ] MetaMask or Dapper (3d)\n[ ] MyEtherWallet?\n[ ] Hover API (JSON)\n[ ]  \n[ ] Auto-update (1d)\n[ ] HTML5 Player\n[ ] Floflis` apps\n[ ] DApp Store (pluggable on Play Center) (1d)\n[ ] Play Center (2d)\n[ ]  \n[ ] Built-in Ethereum (1d)\n[ ] Message: Tron (TRX) is shitty\n[ ]  \n[ ] Organize app categories (1d)\n[ ]  \n[ ] Menus:\n[ ] User photo\n[ ] User/ETH\n[ ] Docs\n[ ] Books\n[ ] Music\n[ ] Videos\n[ ] Pictures\n[ ] Open Badges\n[ ] Downloads\n[ ] Games (1d)\n[ ] --\n[ ] Bkps ?\n[ ] Apps\n[ ] Settings (2d)\n[ ] --\n[ ] Help (1d)\n[ ] --\n[ ] Power btn | Window btns\n[ ]  \n[ ] #HTML5Versions","creation":1550095446254,"lastModification":1564773397399,"locked":false,"reminderFired":false,"title":"0. A HTML5Apps r1 (Floflis 1) (31/4d)","trashed":false}