{"passwordChecked":false,"archived":false,"attachmentsList":[],"baseCategory":{"color":"-1499549","count":0,"description":"","id":1566179703455,"name":" \u0026 prio"},"checklist":false,"content":"https://pr.olx.com.br/regiao-de-curitiba-e-paranagua/imoveis/aluga-se-kitnet-em-campo-comprido-proximo-a-universidade-positivo-e-ao-mercado-condor-660371926","creation":1567959297345,"lastModification":1567959297345,"locked":false,"reminderFired":false,"title":"Aluga-se kitnet em Campo comprido próximo a Universidade positivo, e ao mercado condor","trashed":true}